konlpy/__init__.py
konlpy/about.py
konlpy/corpus.py
konlpy/csvutils.py
konlpy/data.py
konlpy/downloader.py
konlpy/hangul.py
konlpy/internals.py
konlpy/jvm.py
konlpy/user.py
konlpy/utils.py
konlpy/data/corpus/kobill/1809890.txt
konlpy/data/corpus/kobill/1809891.txt
konlpy/data/corpus/kobill/1809892.txt
konlpy/data/corpus/kobill/1809893.txt
konlpy/data/corpus/kobill/1809894.txt
konlpy/data/corpus/kobill/1809895.txt
konlpy/data/corpus/kobill/1809896.txt
konlpy/data/corpus/kobill/1809897.txt
konlpy/data/corpus/kobill/1809898.txt
konlpy/data/corpus/kobill/1809899.txt
konlpy/data/corpus/kolaw/constitution.txt
konlpy/data/tagset/hannanum.json
konlpy/data/tagset/kkma.json
konlpy/data/tagset/komoran.json
konlpy/data/tagset/mecab.json
konlpy/data/tagset/twitter.json
konlpy/java/aho-corasick.jar
konlpy/java/jhannanum-0.8.4.jar
konlpy/java/kkma-2.0.jar
konlpy/java/komoran-3.0.jar
konlpy/java/open-korean-text-2.1.0.jar
konlpy/java/scala-library-2.12.3.jar
konlpy/java/shineware-common-1.0.jar
konlpy/java/shineware-ds-1.0.jar
konlpy/java/snakeyaml-1.12.jar
konlpy/java/twitter-text-1.14.7.jar
konlpy/java/bin/kr/lucypark/jhannanum/comm/HannanumInterface.class
konlpy/java/bin/kr/lucypark/jhannanum/hannanum/WorkflowFactory.class
konlpy/java/bin/kr/lucypark/kkma/KkmaInterface$1.class
konlpy/java/bin/kr/lucypark/kkma/KkmaInterface$2.class
konlpy/java/bin/kr/lucypark/kkma/KkmaInterface$3.class
konlpy/java/bin/kr/lucypark/kkma/KkmaInterface$4.class
konlpy/java/bin/kr/lucypark/kkma/KkmaInterface.class
konlpy/java/bin/kr/lucypark/komoran/KomoranInterface.class
konlpy/java/bin/kr/lucypark/okt/OktInterface.class
konlpy/java/conf/plugin/MajorPlugin/MorphAnalyzer/ChartMorphAnalyzer.json
konlpy/java/conf/plugin/MajorPlugin/PosTagger/HmmPosTagger.json
konlpy/java/conf/plugin/SupplementPlugin/MorphemeProcessor/SimpleMAResult09.json
konlpy/java/conf/plugin/SupplementPlugin/MorphemeProcessor/SimpleMAResult22.json
konlpy-0.5.1.dist-info/METADATA
konlpy-0.5.1.dist-info/RECORD
konlpy-0.5.1.dist-info/WHEEL
konlpy-0.5.1.dist-info/top_level.txt
