Metadata-Version: 1.1
Name: konlpy
Version: 0.5.1
Summary: Python package for Korean natural language processing.
Home-page: http://konlpy.org
Author: Team KoNLPy
Author-email: konlpy@googlegroups.com
License: GPL v3
Keywords: Korean,CJK,NLP,natural language processing,CL,computational linguistics,tagging,tokenizing,linguistics,text analytics
Platform: UNKNOWN
Classifier: Intended Audience :: Developers
Classifier: Intended Audience :: Education
Classifier: Intended Audience :: Information Technology
Classifier: Intended Audience :: Science/Research
Classifier: Programming Language :: Python :: 2.7
Classifier: Programming Language :: Python :: 3.6
Classifier: Topic :: Scientific/Engineering
Classifier: Topic :: Scientific/Engineering :: Artificial Intelligence
Classifier: Topic :: Scientific/Engineering :: Information Analysis
Classifier: Topic :: Text Processing
Classifier: Topic :: Text Processing :: Filters
Classifier: Topic :: Text Processing :: General
Classifier: Topic :: Text Processing :: Linguistic
Classifier: Development Status :: 4 - Beta
Classifier: License :: OSI Approved :: GNU General Public License v3 or later (GPLv3+)
